{"id":"VariableCollectionId:825:22637","name":"Responsive","modes":{"825:4":"Desktop","825:5":"Mobile","825:6":"Tablet"},"variableIds":["VariableID:825:22638","VariableID:825:22639","VariableID:825:22640","VariableID:825:22641"],"variables":[{"id":"VariableID:825:22638","name":"Device Width","description":"","type":"FLOAT","valuesByMode":{"825:4":1200,"825:5":375,"825:6":768},"resolvedValuesByMode":{"825:4":{"resolvedValue":1200,"alias":null},"825:5":{"resolvedValue":375,"alias":null},"825:6":{"resolvedValue":768,"alias":null}},"scopes":["WIDTH_HEIGHT"],"hiddenFromPublishing":false,"codeSyntax":{"WEB":"var(--sds-responsive-device-width)"}},{"id":"VariableID:825:22639","name":"Root Font Size","description":"","type":"FLOAT","valuesByMode":{"825:4":{"type":"VARIABLE_ALIAS","id":"VariableID:825:22681"},"825:5":16,"825:6":16},"resolvedValuesByMode":{"825:4":{"resolvedValue":16,"alias":"VariableID:825:22681","aliasName":"Scale 03"},"825:5":{"resolvedValue":16,"alias":null},"825:6":{"resolvedValue":16,"alias":null}},"scopes":[],"hiddenFromPublishing":false,"codeSyntax":{"WEB":"var(--sds-responsive-root-font-size)"}},{"id":"VariableID:825:22640","name":"Scale","description":"","type":"FLOAT","valuesByMode":{"825:4":1,"825:5":1.25,"825:6":1},"resolvedValuesByMode":{"825:4":{"resolvedValue":1,"alias":null},"825:5":{"resolvedValue":1.25,"alias":null},"825:6":{"resolvedValue":1,"alias":null}},"scopes":[],"hiddenFromPublishing":false,"codeSyntax":{"WEB":"var(--sds-responsive-scale)"}},{"id":"VariableID:825:22641","name":"Device","description":"","type":"STRING","valuesByMode":{"825:4":"desktop","825:5":"mobile","825:6":"tablet"},"resolvedValuesByMode":{"825:4":{"resolvedValue":"desktop","alias":null},"825:5":{"resolvedValue":"mobile","alias":null},"825:6":{"resolvedValue":"tablet","alias":null}},"scopes":["ALL_SCOPES"],"hiddenFromPublishing":false,"codeSyntax":{"WEB":"var(--sds-responsive-device)"}}]}